brokenlinks/__init__.py
brokenlinks/confs.py
brokenlinks/middleware.py
brokenlinks/models.py
brokenlinks/management/__init__.py
brokenlinks/management/commands/__init__.py
brokenlinks/management/commands/createbrokenlinksconfs.py
django_brokenlinks-0.1.1.dist-info/DESCRIPTION.rst
django_brokenlinks-0.1.1.dist-info/METADATA
django_brokenlinks-0.1.1.dist-info/RECORD
django_brokenlinks-0.1.1.dist-info/WHEEL
django_brokenlinks-0.1.1.dist-info/metadata.json
django_brokenlinks-0.1.1.dist-info/top_level.txt
