Metadata-Version: 2.0
Name: django-brokenlinks
Version: 0.1.1
Summary: reusable django app to log crawlers hitting many 404 pages.
Home-page: https://github.com/wtayyeb/django-brokenlinks
Author: wtayyeb
Author-email: wtayyeb@gmail.com
License: MIT
Keywords: django brokenlinks
Platform: any
Classifier: Development Status :: 5 - Production/Stable
Classifier: Environment :: Web Environment
Classifier: Framework :: Django
Classifier: Intended Audience :: Developers
Classifier: Natural Language :: English
Classifier: License :: OSI Approved :: MIT License
Classifier: Operating System :: OS Independent
Classifier: Programming Language :: Python
Classifier: Topic :: Utilities
Requires-Dist: django-appconf
